quartcord/__init__.py
quartcord/_http.py
quartcord/client.py
quartcord/configs.py
quartcord/exceptions.py
quartcord/utils.py
quartcord/models/__init__.py
quartcord/models/base.py
quartcord/models/connections.py
quartcord/models/guild.py
quartcord/models/integration.py
quartcord/models/user.py
quartcord-1.0.1.dist-info/LICENSE
quartcord-1.0.1.dist-info/METADATA
quartcord-1.0.1.dist-info/WHEEL
quartcord-1.0.1.dist-info/top_level.txt
quartcord-1.0.1.dist-info/RECORD
