Metadata-Version: 2.1
Name: quartcord
Version: 1.0.1
Summary: Discord OAuth2 extension for Quart.
Home-page: https://github.com/Sn1F3rt/quartcord
Author: Sayan Bhattacharyya
Author-email: sayan@sn1f3rt.me
License: MIT
Project-URL: Documentation, https://quartcord.readthedocs.io/en/latest/
Project-URL: Issue tracker, https://github.com/Sn1F3rt/quartcord/issues
Project-URL: Support, https://fumes.top/community
Classifier: Development Status :: 5 - Production/Stable
Classifier: License :: OSI Approved :: MIT License
Classifier: Intended Audience :: Developers
Classifier: Natural Language :: English
Classifier: Operating System :: OS Independent
Classifier: Programming Language :: Python :: 3.8
Classifier: Programming Language :: Python :: 3.9
Classifier: Programming Language :: Python :: 3.10
Classifier: Programming Language :: Python :: 3.11
Classifier: Topic :: Internet
Classifier: Topic :: Software Development :: Libraries
Classifier: Topic :: Software Development :: Libraries :: Python Modules
Classifier: Topic :: Utilities
Requires-Python: >=3.8.0
License-File: LICENSE
Requires-Dist: Quart
Requires-Dist: pyjwt
Requires-Dist: aiohttp
Requires-Dist: oauthlib
Requires-Dist: discord.py
Requires-Dist: cachetools
Requires-Dist: Async-OAuthlib
